FizzBuzz.py
fizzbuzz_co-0.0.5.dist-info/LICENSE.txt
fizzbuzz_co-0.0.5.dist-info/METADATA
fizzbuzz_co-0.0.5.dist-info/WHEEL
fizzbuzz_co-0.0.5.dist-info/top_level.txt
fizzbuzz_co-0.0.5.dist-info/RECORD
