Metadata-Version: 2.1
Name: fizzbuzz-co
Version: 0.0.5
Summary: FizzBuzz For Corporate Practices
Home-page: https://github.com/Si-ja/FizzBuzz-Co..git
Author: Si_ja
Author-email: none@none.none
License: UNKNOWN
Platform: UNKNOWN
